{
  "fetched_at": "2026-02-24T17:15:50.477719",
  "channel_id": "UCdgOMA7WO48MYimj6q6mvNQ",
  "videos": [
    {
      "video_id": "3jtmjact_Ns",
      "title": "Top 17 Blanks for Custom Printing #oversizedtshirt #tshirtwholesaler #tshirtmanufacturerindelhi",
      "views": 70469,
      "likes": 934,
      "comments": 87,
      "published": "2025-06-21T13:30:09Z"
    },
    {
      "video_id": "jRoBfrs55LY",
      "title": "Bulk 240gsm French Terry | 12 Trending Shades #oversizedtshirt #tshirtwholesaler",
      "views": 38813,
      "likes": 465,
      "comments": 87,
      "published": "2025-05-24T13:30:38Z"
    },
    {
      "video_id": "j22oJ91E4t8",
      "title": "Plain T-Shirts 2025 — New Colors Just Landed 🚀 #oversizedtshirt #tshirtwholesaler",
      "views": 13586,
      "likes": 370,
      "comments": 79,
      "published": "2025-06-14T13:30:43Z"
    },
    {
      "video_id": "VedUV3-bCvQ",
      "title": "India’s Best Acidwash Oversized T-Shirt? 🔥 #acidwash #stonewash #oversizedtshirt #tshirtwholesaler",
      "views": 12712,
      "likes": 413,
      "comments": 59,
      "published": "2025-06-07T13:30:34Z"
    },
    {
      "video_id": "Ic16Ms2vqaY",
      "title": "240gsm French Terry | 8 Colors Solid Plain",
      "views": 8454,
      "likes": 170,
      "comments": 104,
      "published": "2025-05-17T13:30:06Z"
    },
    {
      "video_id": "cDNd137z7TI",
      "title": "Plain Hoodies Sweatshirt | Winter Item #wholesale #customprinting",
      "views": 7663,
      "likes": 214,
      "comments": 55,
      "published": "2025-11-15T13:30:46Z"
    },
    {
      "video_id": "F-zdRRSs370",
      "title": "How to Order from BulkPlainTshirt.com | B2B Website for Blanks - Perfect for Custom Pritning",
      "views": 7504,
      "likes": 139,
      "comments": 23,
      "published": "2025-08-16T13:30:11Z"
    },
    {
      "video_id": "-_BG3bjqk0w",
      "title": "4 New Updates #dropshipping #customprinting #plaintshirt",
      "views": 7007,
      "likes": 279,
      "comments": 79,
      "published": "2025-07-26T13:30:00Z"
    },
    {
      "video_id": "-uZrijeKiQs",
      "title": "Boxy Fit T shirt - Solid Colors #oversizedtshirt #plaintshirt #wholesale",
      "views": 6998,
      "likes": 233,
      "comments": 35,
      "published": "2025-10-18T13:30:00Z"
    },
    {
      "video_id": "UBJkkdc6tFc",
      "title": "How Train Shipping works? One Day Delivery #plaintshirt #dropshipping #hoodies",
      "views": 6904,
      "likes": 120,
      "comments": 40,
      "published": "2025-11-01T13:30:30Z"
    },
    {
      "video_id": "bguG0OOQIRE",
      "title": "Ab Automatic Logout Nahi Hoga | Login BulkPlainTshirt.com #ecommerce #dropshipping #plaintshirt",
      "views": 6769,
      "likes": 121,
      "comments": 29,
      "published": "2025-07-19T13:30:37Z"
    },
    {
      "video_id": "UT2i4KYIGSE",
      "title": "Install App - BulkPlainTshirt.com #oversizedtshirt #tshirtwholesaler",
      "views": 6517,
      "likes": 161,
      "comments": 35,
      "published": "2025-06-28T13:30:25Z"
    },
    {
      "video_id": "WnFJ28T2GUE",
      "title": "Plain Hoodie 430gsm Rates, color | Sale91.com #wintercollection #plainhoodies #customprinting",
      "views": 6355,
      "likes": 170,
      "comments": 45,
      "published": "2025-12-13T13:30:37Z"
    },
    {
      "video_id": "g59HlKpVlEY",
      "title": "Cotton Hoodie 320gsm - Rates, Fabric etc at sale91.com #wholesale #hoodies #customprinting",
      "views": 6124,
      "likes": 126,
      "comments": 13,
      "published": "2025-12-06T13:31:00Z"
    },
    {
      "video_id": "-m4FGCdqfoc",
      "title": "Dropshipping New Option Made Easier #dropshipping #dropship #plaintshirt #wholesale",
      "views": 6007,
      "likes": 177,
      "comments": 33,
      "published": "2025-08-09T13:30:00Z"
    },
    {
      "video_id": "Z1zB5CIDpfA",
      "title": "Dropshipping through BulkPlainTshirt.com #dropshipping #plaintshirt",
      "views": 5894,
      "likes": 132,
      "comments": 33,
      "published": "2025-08-23T13:30:36Z"
    },
    {
      "video_id": "QNdl56GJDts",
      "title": "To our Dealers and Wholesalers #plaintshirt #customprinting",
      "views": 5716,
      "likes": 165,
      "comments": 17,
      "published": "2025-11-22T13:30:26Z"
    },
    {
      "video_id": "B6u6n6sXj0M",
      "title": "Plain Zipper Hoodies | Winter 320gsm, 430gsm #hoodie #hoodies #wintercollection #plaintshirt",
      "views": 5701,
      "likes": 165,
      "comments": 25,
      "published": "2025-09-27T13:30:10Z"
    },
    {
      "video_id": "-Swb30-I7nA",
      "title": "How to Download Bill and Track Your Order | #BulkPlainTshirt.com #plaintshirt #dropshipping",
      "views": 5301,
      "likes": 50,
      "comments": 3,
      "published": "2025-08-12T14:30:43Z"
    },
    {
      "video_id": "VljsTy3Q8Dk",
      "title": "Bill From Dispatch From option in EwayBill | GST and Dispatch both from different state #easybilling",
      "views": 5137,
      "likes": 145,
      "comments": 24,
      "published": "2025-11-08T13:30:37Z"
    },
    {
      "video_id": "RyCCY33-o6c",
      "title": "Zipper Plain Hoodie Rates, color | Sale91.com #wintercollection #plainhoodies #customprinting",
      "views": 5067,
      "likes": 127,
      "comments": 40,
      "published": "2025-12-20T13:30:35Z"
    },
    {
      "video_id": "NGLIAl9dZ5E",
      "title": "Best Dropshipping Model in India #plaintshirt #wholesale #dropshipping",
      "views": 5053,
      "likes": 135,
      "comments": 52,
      "published": "2025-10-25T13:30:18Z"
    },
    {
      "video_id": "0774zhOVZB8",
      "title": "New Stock aate hi Sabse Pehle Pata Chalega | Stock Alert ON kar lo",
      "views": 4899,
      "likes": 82,
      "comments": 17,
      "published": "2025-07-11T13:30:01Z"
    },
    {
      "video_id": "iVghobj1PQ8",
      "title": "Plain Hoodies within 2 days PAN India | Blanks #dropshipping #oversizedtshirt",
      "views": 4495,
      "likes": 102,
      "comments": 39,
      "published": "2025-10-04T13:30:45Z"
    },
    {
      "video_id": "rjZiy1-3P6M",
      "title": "BLANKS - Heavy Hoodies, Drop shoulder Tshirts | Print and Sell",
      "views": 4380,
      "likes": 128,
      "comments": 30,
      "published": "2025-10-11T13:30:57Z"
    },
    {
      "video_id": "m-O6xjKwYmw",
      "title": "Cotton Sweatshirt 320gsm - Rates, Fabric etc at sale91.com #wholesale #sweatshirt #customprinting",
      "views": 4312,
      "likes": 80,
      "comments": 25,
      "published": "2025-12-10T13:30:55Z"
    },
    {
      "video_id": "gDb1GyBpkv0",
      "title": "Diwali Shipment Delay | Better Solution #oversizedtshirt #oversizedtshirts #wholesale #plaintshirt",
      "views": 4120,
      "likes": 91,
      "comments": 19,
      "published": "2025-10-15T13:30:44Z"
    },
    {
      "video_id": "DLSiLK2r-1o",
      "title": "Call 9336695049 if no reply on WhatsApp",
      "views": 4077,
      "likes": 115,
      "comments": 19,
      "published": "2025-11-29T13:30:24Z"
    },
    {
      "video_id": "J6FSGm5bJoY",
      "title": "AcidWash Oversize T-Shirts — 6 NEW COLORS",
      "views": 3569,
      "likes": 131,
      "comments": 53,
      "published": "2026-02-21T15:30:21Z"
    },
    {
      "video_id": "Vwg-lChShx4",
      "title": "How do I co-ordinare with Printers #tshirtmanufacturer #oversizedtshirt #customprinting #plaintshirt",
      "views": 3367,
      "likes": 115,
      "comments": 15,
      "published": "2026-01-10T13:30:41Z"
    },
    {
      "video_id": "gOMVasctvTQ",
      "title": "Winter Items Out of Stock Solution | Sale91.com #tshirtmanufacturer #plaintshirt #plainhoodies",
      "views": 3298,
      "likes": 88,
      "comments": 13,
      "published": "2026-01-03T13:30:52Z"
    },
    {
      "video_id": "8NgnQN3oJQE",
      "title": "Final Winter Update - New products and colors",
      "views": 3281,
      "likes": 81,
      "comments": 98,
      "published": "2025-08-02T13:30:06Z"
    },
    {
      "video_id": "7YNZfdzkQOY",
      "title": "Women's oversized t-shirts India 2026 - sale91.com",
      "views": 2840,
      "likes": 79,
      "comments": 64,
      "published": "2026-01-31T13:30:18Z"
    },
    {
      "video_id": "hwetf1NFVME",
      "title": "Delhi to Your Train Station | sale91.com #plaintshirt #customprinting #tshirtmanufacturer",
      "views": 2743,
      "likes": 87,
      "comments": 23,
      "published": "2025-12-31T13:30:49Z"
    },
    {
      "video_id": "J5g_DfyxxW8",
      "title": "BulkPlainTShirt.com Shipping Methods Explained: Same Day or Next Day Cost Effective Delivery",
      "views": 2618,
      "likes": 55,
      "comments": 38,
      "published": "2025-05-31T13:30:27Z"
    },
    {
      "video_id": "VlvERpb1V3k",
      "title": "Do You Do Embroidery? Let’s Work Together #embroidery #embroidary #machineembroidery #embroiderer",
      "views": 2569,
      "likes": 70,
      "comments": 26,
      "published": "2026-01-21T13:30:38Z"
    },
    {
      "video_id": "j71qiNc-qio",
      "title": "How I Started A Plain T-Shirt Business with ₹0 Investment | Sale91 Journey & Business Strategy",
      "views": 2389,
      "likes": 69,
      "comments": 42,
      "published": "2026-01-17T13:30:06Z"
    },
    {
      "video_id": "eDMWP2WgE0U",
      "title": "My Apology For Delayed Responses",
      "views": 2343,
      "likes": 59,
      "comments": 75,
      "published": "2025-09-20T13:30:45Z"
    },
    {
      "video_id": "ewB9cZQVKDE",
      "title": "6 Shipping Method Explained on BulkPlainTshirt.com",
      "views": 1950,
      "likes": 33,
      "comments": 22,
      "published": "2025-08-20T13:30:06Z"
    },
    {
      "video_id": "Adnff51oepo",
      "title": "How to Get Easy Bank Loans for Your Business (Secret Strategy) #BusinessTips #Entrepreneurship",
      "views": 1797,
      "likes": 57,
      "comments": 12,
      "published": "2026-01-28T13:30:23Z"
    },
    {
      "video_id": "F6R8WhCGc8Y",
      "title": "Best Custom T-Shirt Printing Vendors in India | DTG DTF Screen Printing Embroidery Service Provider",
      "views": 1626,
      "likes": 76,
      "comments": 41,
      "published": "2026-02-14T16:02:51Z"
    },
    {
      "video_id": "E1B-HKoek5Y",
      "title": "Low Margin vs High Margin: Best Strategy for Wholesale Business? #ProfitMargin #BusinessStrategy",
      "views": 1625,
      "likes": 63,
      "comments": 48,
      "published": "2026-01-24T13:30:06Z"
    },
    {
      "video_id": "rgoOKU5jLMQ",
      "title": "How do I work?",
      "views": 1498,
      "likes": 62,
      "comments": 59,
      "published": "2025-07-05T13:30:52Z"
    },
    {
      "video_id": "d84ZSj-L8IQ",
      "title": "True Dropshipping | BulkPlainTshirt.com #dropshipping #dropship #plaintshirt ",
      "views": 1376,
      "likes": 51,
      "comments": 15,
      "published": "2025-08-30T13:30:39Z"
    },
    {
      "video_id": "MKgpoyx3SyU",
      "title": "What is Zero Contact Dropshipping? How does it work in 2025?",
      "views": 1239,
      "likes": 32,
      "comments": 24,
      "published": "2025-09-13T13:30:22Z"
    },
    {
      "video_id": "dm-3wqKPkic",
      "title": "Never Run Out of Stock Again: The Winter Hoodie Strategy | sale91.com",
      "views": 966,
      "likes": 21,
      "comments": 23,
      "published": "2025-12-27T13:30:06Z"
    },
    {
      "video_id": "vXyJAEj0HBQ",
      "title": "What is dropshipping? How does it work in 2025? #dropshipping #plaintshirt",
      "views": 846,
      "likes": 24,
      "comments": 36,
      "published": "2025-09-06T13:30:06Z"
    },
    {
      "video_id": "_I-OEit03dc",
      "title": "Own Knitted Blank Wears ￼is live",
      "views": 324,
      "likes": 9,
      "comments": 11,
      "published": "2026-02-05T06:19:50Z"
    },
    {
      "video_id": "LoLw9InfKNc",
      "title": "Add GST Number to sale91.com",
      "views": 303,
      "likes": 4,
      "comments": 2,
      "published": "2026-02-23T06:11:02Z"
    },
    {
      "video_id": "9FZgeg_0l5Y",
      "title": "FQA - BulkPlainTshirt.com",
      "views": 0,
      "likes": 4,
      "comments": 0,
      "published": "2025-09-04T03:12:21Z"
    }
  ],
  "top_comments": [
    {
      "text": "Bhaii aap open price deta hoo aapke yee quality bhaut badiya hain. Jisko lena hain vo lo nahi lena toh mat lo. Dusera suppliers na toh rate open rakhte hain aur kesa dusera ko kaat lun asse rakhte hai",
      "likes": 10,
      "video_title": "Top 17 Blanks for Custom Printing #oversizedtshirt #tshirtwh"
    },
    {
      "text": "Bro could you consider royal blue dropshoulder. Very good demand for it. Also peach colour",
      "likes": 7,
      "video_title": "Top 17 Blanks for Custom Printing #oversizedtshirt #tshirtwh"
    },
    {
      "text": "Please improve stitching quality don't use plastic for stitch lock instead interlock. Only issue. Rest fabric is good, I have to buy in a good quantity just refrained due to stitching.\nCan it be impro",
      "likes": 3,
      "video_title": "Plain T-Shirts 2025 — New Colors Just Landed 🚀 #oversizedtsh"
    },
    {
      "text": "Ordered the new powder blue tshirt. Let's see..",
      "likes": 3,
      "video_title": "240gsm French Terry | 8 Colors Solid Plain"
    },
    {
      "text": "Add more colors in every stock",
      "likes": 2,
      "video_title": "Top 17 Blanks for Custom Printing #oversizedtshirt #tshirtwh"
    },
    {
      "text": "Regular size and polo me 48 size bhi le aayo. Delhi or delhi bagal wale haryana me 48 ke demand rehti hai.",
      "likes": 1,
      "video_title": "Top 17 Blanks for Custom Printing #oversizedtshirt #tshirtwh"
    },
    {
      "text": "Sir plz stock wapss se bharo bhoot sara out of stock ho gaya ha to mujhe chhajiye is leye ham sab bethe ha jaldi jaldi banao aap",
      "likes": 1,
      "video_title": "Top 17 Blanks for Custom Printing #oversizedtshirt #tshirtwh"
    },
    {
      "text": "Search \"sale91.com\" - order bulk or samples from website.\n\nWhatsApp to chat - https://whatsapp.sale91.com",
      "likes": 1,
      "video_title": "Bulk 240gsm French Terry | 12 Trending Shades #oversizedtshi"
    },
    {
      "text": "bhai grey or cream color add kriye ye jyda premium touch dete h .",
      "likes": 1,
      "video_title": "Bulk 240gsm French Terry | 12 Trending Shades #oversizedtshi"
    },
    {
      "text": "Premium quality i must say all my customers like the quality",
      "likes": 1,
      "video_title": "Bulk 240gsm French Terry | 12 Trending Shades #oversizedtshi"
    },
    {
      "text": "Army green? Coffee brown ni kehte kya ise🙂",
      "likes": 1,
      "video_title": "Bulk 240gsm French Terry | 12 Trending Shades #oversizedtshi"
    },
    {
      "text": "Bhai premium quality wale difference plain t-shirt Nepal Mei delivery kar sakte ha",
      "likes": 1,
      "video_title": "Bulk 240gsm French Terry | 12 Trending Shades #oversizedtshi"
    },
    {
      "text": "Do you make 3xl",
      "likes": 1,
      "video_title": "Bulk 240gsm French Terry | 12 Trending Shades #oversizedtshi"
    },
    {
      "text": "Bro we want 430 gsm sweatpants(not black), start with gray. Plzzzzzzzzzzzzzzz😊",
      "likes": 1,
      "video_title": "Plain T-Shirts 2025 — New Colors Just Landed 🚀 #oversizedtsh"
    },
    {
      "text": "Regular fit 240gsm",
      "likes": 1,
      "video_title": "Plain T-Shirts 2025 — New Colors Just Landed 🚀 #oversizedtsh"
    },
    {
      "text": "Regular fit 240gsm bhi laiye",
      "likes": 1,
      "video_title": "Plain T-Shirts 2025 — New Colors Just Landed 🚀 #oversizedtsh"
    },
    {
      "text": "Need more colours in acid wash 😢",
      "likes": 1,
      "video_title": "India’s Best Acidwash Oversized T-Shirt? 🔥 #acidwash #stonew"
    },
    {
      "text": "Till when you will launch more colours on acid wash OS",
      "likes": 1,
      "video_title": "India’s Best Acidwash Oversized T-Shirt? 🔥 #acidwash #stonew"
    },
    {
      "text": "Bhai 1pc par delivery charge kitna lagega",
      "likes": 1,
      "video_title": "India’s Best Acidwash Oversized T-Shirt? 🔥 #acidwash #stonew"
    },
    {
      "text": "Sir cash on delivery available",
      "likes": 1,
      "video_title": "India’s Best Acidwash Oversized T-Shirt? 🔥 #acidwash #stonew"
    },
    {
      "text": "Ordered lavander one let's see 🥂🤟🏻",
      "likes": 1,
      "video_title": "240gsm French Terry | 8 Colors Solid Plain"
    },
    {
      "text": "Add more colors atleast 20 colors in 240 gsm \nAnd make ultra quality and proper stitching as well",
      "likes": 1,
      "video_title": "240gsm French Terry | 8 Colors Solid Plain"
    },
    {
      "text": "I ordered 6 tshirt with different categories \nLike 2 240 gsm oversized \nAcidwash RF\nacidwash OS\nPremium polo \n2 Bio Rneck\n\nLet's See The Quality After 8-10 Days",
      "likes": 1,
      "video_title": "240gsm French Terry | 8 Colors Solid Plain"
    },
    {
      "text": "Search \"sale91.com\" - order bulk or samples from website.\n\nWhatsApp to chat - https://whatsapp.sale91.com",
      "likes": 0,
      "video_title": "Top 17 Blanks for Custom Printing #oversizedtshirt #tshirtwh"
    },
    {
      "text": "Kindly try for double stitching in os tshirts  because single stitching is less stable",
      "likes": 0,
      "video_title": "Top 17 Blanks for Custom Printing #oversizedtshirt #tshirtwh"
    },
    {
      "text": "Add full sleeve t shirts this winter if possible",
      "likes": 0,
      "video_title": "Top 17 Blanks for Custom Printing #oversizedtshirt #tshirtwh"
    },
    {
      "text": "Bhai mockup dene se print karwak e deta ho",
      "likes": 0,
      "video_title": "Top 17 Blanks for Custom Printing #oversizedtshirt #tshirtwh"
    },
    {
      "text": "102 wali m or colour add kro sirf black h usme",
      "likes": 0,
      "video_title": "Top 17 Blanks for Custom Printing #oversizedtshirt #tshirtwh"
    },
    {
      "text": "Acidewash hodies la sakte hain is winter me or acide wash me colour variety laiye.",
      "likes": 0,
      "video_title": "Top 17 Blanks for Custom Printing #oversizedtshirt #tshirtwh"
    },
    {
      "text": "Bro can't you make a website or service that will help retailers to buy dtf print  tshirts. Since you have decreased the MOU ... So it's easy for us to order 10 thsirts , with dtf prints on it ... Sel",
      "likes": 0,
      "video_title": "Top 17 Blanks for Custom Printing #oversizedtshirt #tshirtwh"
    }
  ]
}