{
  "target_sub": "r/PrintOnDemand",
  "posting_time": "Weekday morning, 9-11 AM IST",
  "title": "Ordered royal blue oversized tees in bulk. Whole batch rejected in 2 weeks.",
  "body": "Got burned last month and still annoyed about it, so sharing the details so you don't repeat my mistake.\n\nClient wanted 500 royal blue oversized t-shirts — 240 GSM, supposed to be heavy and durable. I didn't do my homework before placing the order. Two weeks in, everything came back rejected.\n\nColor bled all over the clients' prints (dye rub test would've caught this in 30 seconds). Fabric felt cheaper than it should at that weight. And after one wash, the sizing shifted — what fit oversized now looked regular.\n\nTurns out I skipped three basic checks:\n\n**Dye rub test** — wet the fabric and rub it hard on white cloth. If color bleeds, you know the dye isn't set. Dark colors especially need this.\n\n**Weigh the fabric yourself** — grab a meter and scale it. If it claims 240 GSM but weighs way less, you got scammed on thickness.\n\n**Check the yarn type** — combed ring-spun cotton vs. cheap open-end makes a massive difference in feel, even at the same GSM. One feels rough, one feels soft.\n\nDid all three checks on my next order. No returns since.\n\n₹1 lakh down the drain before I figured this out.\n\nFull breakdown with photos: https://www.bulkplaintshirt.com/p/royal-blue-240-gsm-oversized-t-shirt-wholesale-3-quality.html\n\nAnyone else had dark-colored blanks bleed on their clients' prints?",
  "engagement_plan": [
    "Reply to every comment within 12 hours with genuine troubleshooting advice.",
    "Spend 10 minutes commenting helpfully on other posts in r/PrintOnDemand today (no links) — focus on dye-related or GSM quality threads.",
    "Do NOT cross-post to another subreddit today."
  ],
  "hero_image_url": "https://www.bulkplaintshirt.com/p/royal-blue-240-gsm-oversized-t-shirt-wholesale-3-quality-hero.webp",
  "blog_url": "https://www.bulkplaintshirt.com/p/royal-blue-240-gsm-oversized-t-shirt-wholesale-3-quality.html"
}