{
  "target_sub": "r/screenprinting",
  "posting_time": "Weekday morning, 9-11 AM IST",
  "title": "Set up a 24/7 live warehouse feed. Clients stopped asking if stock is real.",
  "body": "Sounds weird but hear me out.\n\nI run a plain blank supplier out of Tiruppur. Been doing B2B for years — printers, POD shops, small brands. Same problem every week: \"Do you actually have 500 pieces in stock?\" \"Can I see the warehouse?\" \"How do I know you're not dropshipping from someone else?\"\n\nTried sending photos. Tried same-day video calls. Still got the trust questions. Printing businesses have been burned too many times by suppliers who promise stock and then scramble.\n\nFinally just said screw it — pointed a camera at the warehouse floor and made it live 24/7 on YouTube. No editing, no script, just the actual space running. Fabric rolls, stacks of blanks, people packing orders.\n\nWeirdest thing: inquiries went up, questions went down. People browse at 2 AM, see the live feed, place orders same night. One guy told me he watches it while deciding on his bulk order just to feel confident the stock exists.\n\nCost maybe ₹15k to set up the camera and streaming setup. Converts better than any sales pitch I've tried.\n\nFull breakdown with photos: https://www.bulkplaintshirt.com/p/247-live-warehouse-tour-bulkplaintshirtcom-tiruppur-plain-t.html\n\nAnyone else tried something like this for transparency?",
  "engagement_plan": [
    "Reply to every comment within 12 hours.",
    "Spend 10 minutes commenting helpfully on other posts in r/screenprinting today (no links).",
    "Do NOT cross-post to another subreddit today."
  ],
  "hero_image_url": "https://www.bulkplaintshirt.com/p/247-live-warehouse-tour-bulkplaintshirtcom-tiruppur-plain-t-hero.webp",
  "blog_url": "https://www.bulkplaintshirt.com/p/247-live-warehouse-tour-bulkplaintshirtcom-tiruppur-plain-t.html"
}